README.md
setup.py
kerfex/__init__.py
kerfex/feature_extraction.py
kerfex.egg-info/PKG-INFO
kerfex.egg-info/SOURCES.txt
kerfex.egg-info/dependency_links.txt
kerfex.egg-info/requires.txt
kerfex.egg-info/top_level.txt