Metadata-Version: 2.1
Name: kerfex
Version: 0.0.1
Summary: Generic feature extraction using keras pre-built CNN's with imagenet weights.
Home-page: https://github.com/caiocarneloz/kerfex
Author: Caio Carneloz
Author-email: caiocarneloz@gmail.com
License: MIT License
Keywords: keras,feature-extraction,CNN,Imagenet
Platform: UNKNOWN
